zowie/__init__.py
zowie/__main__.py
zowie/exceptions.py
zowie/exit_codes.py
zowie/keyring_utils.py
zowie/main_body.py
zowie/zotero.py
zowie/methods/__init__.py
zowie/methods/base.py
zowie/methods/findercomment.py
zowie/methods/pdfproducer.py
zowie/methods/pdfsubject.py
zowie/methods/wherefrom.py
zowie-1.3.0.dist-info/LICENSE
zowie-1.3.0.dist-info/METADATA
zowie-1.3.0.dist-info/WHEEL
zowie-1.3.0.dist-info/entry_points.txt
zowie-1.3.0.dist-info/top_level.txt
zowie-1.3.0.dist-info/RECORD
