Metadata-Version: 2.1
Name: zowie
Version: 1.3.0
Summary: Write Zotero select links into article attachment files
Home-page: https://github.com/mhucka/zowie
Author: Michael Hucka
Author-email: mhucka@caltech.edu
License: BSD 3-clause
Project-URL: Source Code, https://github.com/mhucka/zowie
Project-URL: Bug Tracker, https://github.com/mhucka/zowie/issues
Keywords: Python,utilities
Classifier: Development Status :: 5 - Production/Stable
Classifier: License :: OSI Approved :: BSD License
Classifier: Intended Audience :: Science/Research
Classifier: Operating System :: MacOS :: MacOS X
Classifier: Programming Language :: Python :: 3.8
Requires-Python: >=3.8
License-File: LICENSE
Requires-Dist: aenum (==3.1.12)
Requires-Dist: biplist (==1.0.3)
Requires-Dist: boltons (==21.0.0)
Requires-Dist: bun (==0.0.8)
Requires-Dist: commonpy (==1.12.3)
Requires-Dist: keyring (==23.2.1)
Requires-Dist: keyrings.alt (==4.1.0)
Requires-Dist: pdfrw (==0.4)
Requires-Dist: plac (==1.3.5)
Requires-Dist: py-applescript (==1.0.2)
Requires-Dist: pyzotero (==1.5.5)
Requires-Dist: pyxattr (==0.8.0)
Requires-Dist: setuptools (>=67.5.1)
Requires-Dist: sidetrack (==2.0.1)
Requires-Dist: pyobjc-core (==9.0.1)
Requires-Dist: pyobjc-framework-AppleScriptKit (==9.0.1)
Requires-Dist: pyobjc-framework-AppleScriptObjC (==9.0.1)
